<?xml version="1.0" encoding="utf-8"?>
<form addrulepath="/administrator/components/com_companies/models/rules">
    <fieldset name="params">
        <field
                name="is_contractor"
                type="radio"
                class="btn-group btn-group-yesno"
                default="0"
                label="COM_COMPANIES_FORM_COMPANY_CONTRACTOR_LABEL"
                description="COM_COMPANIES_FORM_COMPANY_CONTRACTOR_DESC"
                required="true"
                filter="bool"
        >
            <option value="0">JNO</option>
            <option value="1">JYES</option>
        </field>
        <field
                name="is_ndp"
                type="hidden"
                default="0"
        />
        <field
                name="parentID"
                type="list"
                label="COM_COMPANIES_FORM_COMPANY_PARENT_LABEL"
                description="COM_COMPANIES_FORM_COMPANY_PARENT_DESC"
                class="span12"
        >
            <option value=""></option>
        </field>
        <field
                name="id"
                type="hidden"
        />
    </fieldset>
    <fieldset name="general">
        <field
                name="form"
                type="text"
                label="COM_COMPANIES_FORM_COMPANY_FORM_LABEL"
                description="COM_COMPANIES_FORM_COMPANY_FORM_DESC"
                hint="COM_COMPANIES_FORM_COMPANY_FORM_HINT"
                value="varchar"
                required="true"
                maxlength="255"
                class="span12"
        />
        <field
                name="title"
                type="text"
                label="COM_COMPANIES_FORM_COMPANY_TITLE_LABEL"
                description="COM_COMPANIES_FORM_COMPANY_TITLE_DESC"
                hint="COM_COMPANIES_FORM_COMPANY_TITLE_HINT"
                autocomplete="off"
                required="true"
                value="varchar"
                maxlength="255"
                class="span12"
        />
        <field
                name="title_full"
                type="text"
                label="COM_COMPANIES_FORM_COMPANY_TITLE_FULL_LABEL"
                description="COM_COMPANIES_FORM_COMPANY_TITLE_FULL_DESC"
                hint="COM_COMPANIES_FORM_COMPANY_TITLE_FULL_HINT"
                autocomplete="off"
                maxlength="255"
                value="varchar"
                class="span12"
        />
        <field
                name="title_en"
                type="text"
                label="COM_COMPANIES_FORM_COMPANY_TITLE_EN_LABEL"
                description="COM_COMPANIES_FORM_COMPANY_TITLE_EN_DESC"
                hint="COM_COMPANIES_FORM_COMPANY_TITLE_EN_HINT"
                value="varchar"
                maxlength="255"
                autocomplete="off"
                class="span12"
        />
        <field
                name="director_name"
                type="text"
                label="COM_COMPANIES_FORM_COMPANY_DIRECTOR_NAME_LABEL"
                description="COM_COMPANIES_FORM_COMPANY_DIRECTOR_NAME_DESC"
                hint="COM_COMPANIES_FORM_COMPANY_DIRECTOR_NAME_HINT"
                message="COM_COMPANIES_FORM_COMPANY_DIRECTOR_NAME_MESSAGE"
                validate="fio"
                maxlength="255"
                autocomplete="off"
                required="true"
                class="span12"
        />
        <field
                name="director_post"
                type="text"
                label="COM_COMPANIES_FORM_COMPANY_DIRECTOR_POST_LABEL"
                description="COM_COMPANIES_FORM_COMPANY_DIRECTOR_POST_DESC"
                hint="COM_COMPANIES_FORM_COMPANY_DIRECTOR_POST_HINT"
                message="COM_COMPANIES_FORM_COMPANY_DIRECTOR_POST_MESSAGE"
                validate="varchar"
                maxlength="255"
                required="true"
                class="span12"
        />
        <field
                name="comment"
                type="textarea"
                label="COM_COMPANIES_FORM_COMPANY_COMMENT_LABEL"
                description="COM_COMPANIES_FORM_COMPANY_COMMENT_DESC"
                hint="COM_COMPANIES_FORM_COMPANY_COMMENT_HINT"
                autocomplete="off"
                class="span12"
                rows="5"
        />
        <field
                name="activities"
                type="Activity"
                multiple="true"
                label="COM_COMPANIES_FORM_COMPANY_ACTIVITIES_LABEL"
                description="COM_COMPANIES_FORM_COMPANY_ACTIVITIES_DESC"
                class="span12"
        />
    </fieldset>
    <fieldset name="bank">
        <field
                name="inn"
                type="text"
                label="COM_COMPANIES_FORM_COMPANY_INN_LABEL"
                description="COM_COMPANIES_FORM_COMPANY_INN_DESC"
                hint="COM_COMPANIES_FORM_COMPANY_INN_HINT"
                autocomplete="off"
                maxlength="12"
                validate="inn"
                class="span12"
        />
        <field
                name="kpp"
                type="text"
                label="COM_COMPANIES_FORM_COMPANY_KPP_LABEL"
                description="COM_COMPANIES_FORM_COMPANY_KPP_DESC"
                hint="COM_COMPANIES_FORM_COMPANY_KPP_HINT"
                autocomplete="off"
                validate="kpp"
                maxlength="12"
                class="span12"
        />
        <field
                name="rs"
                type="text"
                label="COM_COMPANIES_FORM_COMPANY_RS_LABEL"
                description="COM_COMPANIES_FORM_COMPANY_RS_DESC"
                hint="COM_COMPANIES_FORM_COMPANY_RS_HINT"
                autocomplete="off"
                validate="rs"
                maxlength="20"
                class="span12"
        />
        <field
                name="ks"
                type="text"
                label="COM_COMPANIES_FORM_COMPANY_KS_LABEL"
                description="COM_COMPANIES_FORM_COMPANY_KS_DESC"
                hint="COM_COMPANIES_FORM_COMPANY_KS_HINT"
                autocomplete="off"
                validate="rs"
                maxlength="20"
                class="span12"
        />
        <field
                name="bank"
                type="text"
                label="COM_COMPANIES_FORM_COMPANY_BANK_LABEL"
                description="COM_COMPANIES_FORM_COMPANY_BANK_DESC"
                hint="COM_COMPANIES_FORM_COMPANY_BANK_HINT"
                autocomplete="off"
                class="span12"
        />
        <field
                name="bik"
                type="text"
                label="COM_COMPANIES_FORM_COMPANY_BIK_LABEL"
                description="COM_COMPANIES_FORM_COMPANY_BIK_DESC"
                hint="COM_COMPANIES_FORM_COMPANY_BIK_HINT"
                autocomplete="off"
                validate="bik"
                maxlength="10"
                class="span12"
        />
    </fieldset>
    <fieldset name="legal_address">
        <field
                name="legal_city"
                type="list"
                label="COM_COMPANIES_FORM_COMPANY_LEGAL_CITY_LABEL"
                description="COM_COMPANIES_FORM_COMPANY_LEGAL_CITY_DESC"
                required="true"
                class="span12"
                filter="integer"
                validate="city"
        />
        <field
                name="legal_index"
                type="text"
                label="COM_COMPANIES_FORM_COMPANY_LEGAL_INDEX_LABEL"
                description="COM_COMPANIES_FORM_COMPANY_LEGAL_INDEX_DESC"
                hint="COM_COMPANIES_FORM_COMPANY_LEGAL_INDEX_HINT"
                message="COM_COMPANIES_FORM_COMPANY_INDEX_MESSAGE"
                autocomplete="off"
                maxlength="6"
                class="span12"
                validate="index"
        />
        <field
                name="legal_street"
                type="text"
                label="COM_COMPANIES_FORM_COMPANY_LEGAL_STREET_LABEL"
                description="COM_COMPANIES_FORM_COMPANY_LEGAL_STREET_DESC"
                hint="COM_COMPANIES_FORM_COMPANY_LEGAL_STREET_HINT"
                autocomplete="off"
                class="span12"
        />
        <field
                name="legal_house"
                type="text"
                label="COM_COMPANIES_FORM_COMPANY_LEGAL_HOUSE_LABEL"
                description="COM_COMPANIES_FORM_COMPANY_LEGAL_HOUSE_DESC"
                hint="COM_COMPANIES_FORM_COMPANY_LEGAL_HOUSE_HINT"
                autocomplete="off"
                class="span12"
        />
    </fieldset>
    <fieldset name="fact_address">
        <field
                name="fact_city"
                type="list"
                label="COM_COMPANIES_FORM_COMPANY_FACT_CITY_LABEL"
                description="COM_COMPANIES_FORM_COMPANY_FACT_CITY_DESC"
                required="true"
                class="span12"
                filter="integer"
                validate="city"
        />
        <field
                name="fact_index"
                type="text"
                label="COM_COMPANIES_FORM_COMPANY_FACT_INDEX_LABEL"
                description="COM_COMPANIES_FORM_COMPANY_FACT_INDEX_DESC"
                hint="COM_COMPANIES_FORM_COMPANY_FACT_INDEX_HINT"
                message="COM_COMPANIES_FORM_COMPANY_INDEX_MESSAGE"
                autocomplete="off"
                maxlength="6"
                class="span12"
                validate="index"
        />
        <field
                name="fact_street"
                type="text"
                label="COM_COMPANIES_FORM_COMPANY_FACT_STREET_LABEL"
                description="COM_COMPANIES_FORM_COMPANY_FACT_STREET_DESC"
                hint="COM_COMPANIES_FORM_COMPANY_FACT_STREET_HINT"
                autocomplete="off"
                class="span12"
        />
        <field
                name="fact_house"
                type="text"
                label="COM_COMPANIES_FORM_COMPANY_FACT_HOUSE_LABEL"
                description="COM_COMPANIES_FORM_COMPANY_FACT_HOUSE_DESC"
                hint="COM_COMPANIES_FORM_COMPANY_FACT_HOUSE_HINT"
                autocomplete="off"
                class="span12"
        />
    </fieldset>
    <fieldset name="contacts">
        <field
                name="phone_1"
                type="phone"
                label="COM_COMPANIES_FORM_COMPANY_PHONE_1_LABEL"
                description="COM_COMPANIES_FORM_COMPANY_PHONE_1_DESC"
                hint="COM_COMPANIES_FORM_COMPANY_PHONE_HINT"
                message="COM_COMPANIES_FORM_COMPANY_PHONE_1_MESSAGE"
                autocomplete="off"
                inputtype="tel"
                validate="phone"
                maxlength="255"
                class="span12"
        />
        <field
                name="phone_1_additional"
                type="text"
                label="COM_COMPANIES_FORM_COMPANY_PHONE_1_ADDITIONAL_LABEL"
                description="COM_COMPANIES_FORM_COMPANY_PHONE_1_ADDITIONAL_DESC"
                hint="COM_COMPANIES_FORM_COMPANY_PHONE_ADDITIONAL_HINT"
                maxlength="10"
                autocomplete="false"
                class="span12"
        />
        <field
                name="phone_1_comment"
                type="text"
                label="COM_COMPANIES_FORM_COMPANY_PHONE_1_COMMENT_LABEL"
                description="COM_COMPANIES_FORM_COMPANY_PHONE_1_COMMENT_DESC"
                hint="COM_COMPANIES_FORM_COMPANY_PHONE_1_COMMENT_HINT"
                autocomplete="off"
                class="span12"
        />
        <field
                name="phone_2"
                type="phone"
                label="COM_COMPANIES_FORM_COMPANY_PHONE_2_LABEL"
                description="COM_COMPANIES_FORM_COMPANY_PHONE_2_DESC"
                hint="COM_COMPANIES_FORM_COMPANY_PHONE_HINT"
                message="COM_COMPANIES_FORM_COMPANY_PHONE_2_MESSAGE"
                autocomplete="off"
                inputtype="tel"
                validate="phone"
                maxlength="255"
                class="span12"
        />
        <field
                name="phone_2_additional"
                type="text"
                label="COM_COMPANIES_FORM_COMPANY_PHONE_2_ADDITIONAL_LABEL"
                description="COM_COMPANIES_FORM_COMPANY_PHONE_2_ADDITIONAL_DESC"
                hint="COM_COMPANIES_FORM_COMPANY_PHONE_ADDITIONAL_HINT"
                maxlength="10"
                autocomplete="false"
                class="span12"
        />
        <field
                name="phone_2_comment"
                type="text"
                label="COM_COMPANIES_FORM_COMPANY_PHONE_2_COMMENT_LABEL"
                description="COM_COMPANIES_FORM_COMPANY_PHONE_2_COMMENT_DESC"
                hint="COM_COMPANIES_FORM_COMPANY_PHONE_2_COMMENT_HINT"
                autocomplete="off"
                class="span12"
        />
        <field
                name="fax"
                type="text"
                label="COM_COMPANIES_FORM_COMPANY_FAX_LABEL"
                description="COM_COMPANIES_FORM_COMPANY_FAX_DESC"
                hint="COM_COMPANIES_FORM_COMPANY_PHONE_HINT"
                message="COM_COMPANIES_FORM_COMPANY_FAX_MESSAGE"
                autocomplete="off"
                inputtype="tel"
                validate="phone"
                maxlength="255"
                class="span12"
        />
        <field
                name="fax_additional"
                type="text"
                label="COM_COMPANIES_FORM_COMPANY_FAX_ADDITIONAL_LABEL"
                description="COM_COMPANIES_FORM_COMPANY_FAX_ADDITIONAL_DESC"
                hint="COM_COMPANIES_FORM_COMPANY_PHONE_ADDITIONAL_HINT"
                maxlength="10"
                autocomplete="false"
                class="span12"
        />
        <field
                name="email"
                type="email"
                label="COM_COMPANIES_FORM_COMPANY_EMAIL_LABEL"
                description="COM_COMPANIES_FORM_COMPANY_EMAIL_DESC"
                hint="COM_COMPANIES_FORM_COMPANY_EMAIL_HINT"
                validate="email"
                autocomplete="off"
                class="span12 validate-email"
        />
        <field
                name="site"
                type="url"
                label="COM_COMPANIES_FORM_COMPANY_SITE_LABEL"
                description="COM_COMPANIES_FORM_COMPANY_SITE_DESC"
                hint="COM_COMPANIES_FORM_COMPANY_SITE_HINT"
                autocomplete="off"
                validate="url"
                class="span12 validate-url"
        />
        <field
                name="hidden_legal_city_id"
                type="hidden"
                value=""
        />
        <field
                name="hidden_legal_city_title"
                type="hidden"
                value=""
        />
        <field
                name="hidden_fact_city_id"
                type="hidden"
                value=""
        />
        <field
                name="hidden_fact_city_title"
                type="hidden"
                value=""
        />
        <field
                name="hidden_parent_id"
                type="hidden"
                value=""
        />
        <field
                name="hidden_parent_title"
                type="hidden"
                value=""
        />
    </fieldset>
</form>